jupyterlab_vscode_icons_extension/__init__.py
jupyterlab_vscode_icons_extension/_version.py
jupyterlab_vscode_icons_extension/handlers.py
jupyterlab_vscode_icons_extension-1.1.85.data/data/etc/jupyter/jupyter_server_config.d/jupyterlab_vscode_icons_extension.json
jupyterlab_vscode_icons_extension-1.1.85.data/data/share/jupyter/labextensions/jupyterlab_vscode_icons_extension/package.json
jupyterlab_vscode_icons_extension-1.1.85.data/data/share/jupyter/labextensions/jupyterlab_vscode_icons_extension/schemas/jupyterlab_vscode_icons_extension/package.json.orig
jupyterlab_vscode_icons_extension-1.1.85.data/data/share/jupyter/labextensions/jupyterlab_vscode_icons_extension/schemas/jupyterlab_vscode_icons_extension/plugin.json
jupyterlab_vscode_icons_extension-1.1.85.data/data/share/jupyter/labextensions/jupyterlab_vscode_icons_extension/static/426.541458058322187136d6.js
jupyterlab_vscode_icons_extension-1.1.85.data/data/share/jupyter/labextensions/jupyterlab_vscode_icons_extension/static/657.05092362886a809c8105.js
jupyterlab_vscode_icons_extension-1.1.85.data/data/share/jupyter/labextensions/jupyterlab_vscode_icons_extension/static/728.37f024d6ecaddd4e7245.js
jupyterlab_vscode_icons_extension-1.1.85.data/data/share/jupyter/labextensions/jupyterlab_vscode_icons_extension/static/remoteEntry.f94713b506fbc0504f2b.js
jupyterlab_vscode_icons_extension-1.1.85.data/data/share/jupyter/labextensions/jupyterlab_vscode_icons_extension/static/style.js
jupyterlab_vscode_icons_extension-1.1.85.data/data/share/jupyter/labextensions/jupyterlab_vscode_icons_extension/static/third-party-licenses.json
jupyterlab_vscode_icons_extension-1.1.85.data/data/share/jupyter/labextensions/jupyterlab_vscode_icons_extension/install.json
jupyterlab_vscode_icons_extension-1.1.85.dist-info/METADATA
jupyterlab_vscode_icons_extension-1.1.85.dist-info/WHEEL
jupyterlab_vscode_icons_extension-1.1.85.dist-info/licenses/LICENSE
jupyterlab_vscode_icons_extension-1.1.85.dist-info/RECORD
